{
  "basics": {
    "name": "Columba Sanchez",
    "label": "Shidler Undergraduate",
    "picture": "https://github.com/columbaanita.png",
    "email": "columba@hawaii.edu",
    "phone": "808-913-4100",
    "website": "https://columbaanita.github.io",
    "summary": "I am studying for a B.S. in Accounting and MIS at the University of Hawaii. I expect to graduate in Spring, 2025.",
    "location": { "address": "", "postalCode": "96822", "city": "Honolulu", "countryCode": "USA", "region": "Hawaii" },
    "profiles": [
      { "network": "github", "username": "columbaanita", "url": "http://github.com/columbaanita" },
      { "network": "linkedin", "username": "columbasanchez", "url": "https://www.linkedin.com/in/columba-sanchez-3a49162a9/" }
    ]
  },
  "interests": [
    { "name": "Accounting" },
    { "name": "Volleyball" },
    { "name": "Cooking" },
    { "name": "Wellness" },
    { "name": "Technology" }
  ],
  "education": [
    {
      "institution": "University of Hawaii, Honolulu, HI",
      "area": "Accounting and MIS (expected Spring, 2025)",
      "studyType": "B.S.",
      "startDate": "2021-08-01",
      "endDate": "Present",
      "courses": [
      ]
    }
  ],
  "work": [
    {
      "company": "UH Manoa Wahine Volleyball",
      "position": "Team Manager",
      "website": "",
      "startDate": "2022-08-01",
      "endDate": "Present",
      "summary": "",
      "highlights": [
      ]
    }
  ],
  "references": [
    {
      "name": "Available upon request"
    }
  ]
}
